py_mcp_client/__init__.py
py_mcp_client-0.0.8.dist-info/METADATA
py_mcp_client-0.0.8.dist-info/WHEEL
py_mcp_client-0.0.8.dist-info/licenses/LICENSE
py_mcp_client-0.0.8.dist-info/RECORD
