Metadata-Version: 2.4
Name: py-mcp-client
Version: 0.0.8
Summary: A Python client for interacting with MCP servers via Server-Sent Events and JSON-RPC
Project-URL: Homepage, https://github.com/pytincture/py-mcp-client
Project-URL: Repository, https://github.com/pytincture/py-mcp-client.git
Project-URL: Issues, https://github.com/pytincture/py-mcp-client/issues
Author-email: pytincture <schapman1974@gmail.com>
License-File: LICENSE
Classifier: License :: OSI Approved :: MIT License
Classifier: Operating System :: OS Independent
Classifier: Programming Language :: Python :: 3
Requires-Python: >=3.11
